{
    "gnw_ball": {
        "genres": [],
        "players": 1,
        "rating": null
    },
    "gnw_bfight": {
        "genres": [],
        "players": null,
        "rating": null
    },
    "gnw_bjack": {
        "genres": [],
        "players": null,
        "rating": null
    },
    "gnw_boxing": {
        "genres": [],
        "players": null,
        "rating": null
    },
    "gnw_bsweep": {
        "genres": [],
        "players": null,
        "rating": null
    },
    "gnw_cgrab": {
        "genres": [
            "Casual Game"
        ],
        "players": 1,
        "rating": null
    },
    "gnw_chef": {
        "genres": [],
        "players": null,
        "rating": null
    },
    "gnw_climber": {
        "genres": [],
        "players": null,
        "rating": null
    },
    "gnw_dkhockey": {
        "genres": [],
        "players": null,
        "rating": null
    },
    "gnw_dkjr": {
        "genres": [
            "Action"
        ],
        "players": 1,
        "rating": null
    },
    "gnw_dkjrp": {
        "genres": [
            "Action"
        ],
        "players": 1,
        "rating": null
    },
    "gnw_dkong": {
        "genres": [],
        "players": null,
        "rating": null
    },
    "gnw_dkong2": {
        "genres": [],
        "players": null,
        "rating": null
    },
    "gnw_dkong3": {
        "genres": [],
        "players": null,
        "rating": null
    },
    "gnw_fire": {
        "genres": [],
        "players": null,
        "rating": null
    },
    "gnw_fireatk": {
        "genres": [],
        "players": 1,
        "rating": null
    },
    "gnw_fires": {
        "genres": [],
        "players": null,
        "rating": null
    },
    "gnw_flagman": {
        "genres": [],
        "players": 1,
        "rating": null
    },
    "gnw_gcliff": {
        "genres": [],
        "players": null,
        "rating": null
    },
    "gnw_ghouse": {
        "genres": [],
        "players": null,
        "rating": null
    },
    "gnw_helmet": {
        "genres": [],
        "players": null,
        "rating": null
    },
    "gnw_judge": {
        "genres": [],
        "players": null,
        "rating": null
    },
    "gnw_lboat": {
        "genres": [],
        "players": null,
        "rating": null
    },
    "gnw_lion": {
        "genres": [],
        "players": null,
        "rating": null
    },
    "gnw_manhole": {
        "genres": [],
        "players": null,
        "rating": null
    },
    "gnw_manholeg": {
        "genres": [],
        "players": null,
        "rating": null
    },
    "gnw_mario": {
        "genres": [],
        "players": null,
        "rating": null
    },
    "gnw_mariocm": {
        "genres": [],
        "players": null,
        "rating": null
    },
    "gnw_mariocmt": {
        "genres": [],
        "players": null,
        "rating": null
    },
    "gnw_mariotj": {
        "genres": [],
        "players": 1,
        "rating": null
    },
    "gnw_mbaway": {
        "genres": [
            "Action"
        ],
        "players": 1,
        "rating": null
    },
    "gnw_mickdon": {
        "genres": [],
        "players": null,
        "rating": null
    },
    "gnw_mmouse": {
        "genres": [],
        "players": null,
        "rating": null
    },
    "gnw_mmousep": {
        "genres": [],
        "players": null,
        "rating": null
    },
    "gnw_octopus": {
        "genres": [],
        "players": null,
        "rating": null
    },
    "gnw_opanic": {
        "genres": [],
        "players": null,
        "rating": null
    },
    "gnw_pchute": {
        "genres": [
            "Action"
        ],
        "players": 1,
        "rating": null
    },
    "gnw_pinball": {
        "genres": [],
        "players": null,
        "rating": null
    },
    "gnw_popeye": {
        "genres": [],
        "players": null,
        "rating": null
    },
    "gnw_popeyep": {
        "genres": [],
        "players": null,
        "rating": null
    },
    "gnw_rshower": {
        "genres": [],
        "players": null,
        "rating": null
    },
    "gnw_sbuster": {
        "genres": [],
        "players": null,
        "rating": null
    },
    "gnw_smb": {
        "genres": [],
        "players": null,
        "rating": null
    },
    "gnw_snoopyp": {
        "genres": [
            "Action"
        ],
        "players": 1,
        "rating": null
    },
    "gnw_squish": {
        "genres": [],
        "players": null,
        "rating": null
    },
    "gnw_ssparky": {
        "genres": [
            "Action",
            "Action / Breakout games"
        ],
        "players": 1,
        "rating": null
    },
    "gnw_stennis": {
        "genres": [
            "Sports",
            "Sports / Tennis",
            "Action"
        ],
        "players": 1,
        "rating": null
    },
    "gnw_tbridge": {
        "genres": [
            "Puzzle-Game",
            "Action"
        ],
        "players": 1,
        "rating": null
    },
    "gnw_tfish": {
        "genres": [],
        "players": 1,
        "rating": null
    },
    "gnw_vermin": {
        "genres": [
            "Casual Game"
        ],
        "players": 1,
        "rating": null
    },
    "gnw_zelda": {
        "genres": [],
        "players": null,
        "rating": null
    }
}